setup.cfg
setup.py
siridb/__init__.py
siridb/twisted/__init__.py
siridb/twisted/lib/__init__.py
siridb/twisted/lib/client.py
siridb/twisted/lib/datapackage.py
siridb/twisted/lib/defaults.py
siridb/twisted/lib/exceptions.py
siridb/twisted/lib/factory.py
siridb/twisted/lib/protocol.py
siridb/twisted/lib/protomap.py
siridb_connector_twisted.egg-info/PKG-INFO
siridb_connector_twisted.egg-info/SOURCES.txt
siridb_connector_twisted.egg-info/dependency_links.txt
siridb_connector_twisted.egg-info/requires.txt
siridb_connector_twisted.egg-info/top_level.txt
test/test.py