Metadata-Version: 1.1
Name: siridb-connector-twisted
Version: 2.0.5
Summary: SiriDB Connector (using Twisted)
Home-page: https://github.com/transceptor-technology/siridb-connector-twisted
Author: Jeroen van der Heijden
Author-email: jeroen@transceptor.technology
License: UNKNOWN
Download-URL: https://github.com/transceptor-technology/siridb-connector-twisted/tarball/2.0.5
Keywords: siridb,connector,database,client,twisted
Platform: UNKNOWN
Classifier: Development Status :: 4 - Beta
Classifier: Environment :: Other Environment
Classifier: Intended Audience :: Developers
Classifier: License :: OSI Approved :: MIT License
Classifier: Operating System :: OS Independent
Classifier: Programming Language :: Python :: 2
Classifier: Programming Language :: Python :: 3
Classifier: Topic :: Database
Classifier: Topic :: Software Development
